{
                     "name": "GetFinance",
                     "displayName": "Get Finance",
                     "description": "I need money to help me achieve my goals",
                     "productLines": [
                        {
                           "displayName": "Loans",
                           "name": "Loans",
                           "description": "To start up, grow, offer flexibility or manage debt.",
                           "popularProducts": [],
                           "products": [
                              {
                                 "productIdentifier": "96",
                                 "name": "Overdraft",
                                 "dispalyName": "Overdraft",
                                 "shortDescription": "At times your business needs some cashflow flexibility – while you’re waiting for payments to come in, you need to make payments of your own. A Nedbank overdraft facility is the ideal solution, providing working capital finance and unlocking cashflow.",
                                 "productPricing": [
                                    {
                                       "type": "",
                                       "amount": 0,
                                       "frequency": "",
                                       "currency": "",
                                       "description": ""
                                    }
                                 ],
                                 "salesHighlights": [
                                    "Provides the flexibility to borrow or repay as and when your cashflow allows;",
                                    "Making funds accessible quickly and easily through a variety of mechanisms",
                                    "Calculating debit interest on the daily used amount only."
                                 ],
                                 "benefits": [
                                    "Easy access with electronic banking, ATMs and debit cards",
                                    "Competitive, risk-based pricing",
                                    "Immediate access – as soon as your current account is active, you can apply for an overdraft facility and, once approved and the preagreed conditions are met, the facility is made available immediately"
                                 ],
                                 "productOnAPageWebURL": "/content/nedbank/desktop/gt/en/personal/loans/personal-loans/personal-loan.html",
                                 "productAttributeGroup": [
                                    {
                                       "attributeGroupName": "ProductFeatures",
                                       "productAttributes": [
                                          {
                                             "attributeType": "Feature",
                                             "attributeName": "DisplayName",
                                             "isComparable": "false",
                                             "value": ""
                                          },
                                          {
                                             "attributeType": "Feature",
                                             "attributeName": "EntityType",
                                             "value": "BB,CIB,RRB,BB-Attorney,CIB-Attorney,RRB-Attorney"
                                          },
                                          {
                                             "attributeType": "Feature",
                                             "attributeName": "ShowPricing",
                                             "isComparable": "false",
                                             "value": "true",
                                             "valueUnit": "bool"
                                          },
                                          {
                                             "attributeType": "Feature",
                                             "attributeName": "ManageQuantity",
                                             "isComparable": "false",
                                             "value": "1",
                                             "minValue": "1",
                                             "maxValue": "1",
                                             "valueUnit": "number"
                                          },
                                          {
                                             "attributeType": "Feature",
                                             "attributeName": "IsFixedPrice",
                                             "isComparable": "false",
                                             "value": "true",
                                             "valueUnit": "bool"
                                          },
                                          {
                                             "attributeType": "Feature",
                                             "attributeName": "ProductImageURL",
                                             "isComparable": "false",
                                             "value": "/content/dam/nedbank-onboarding/assets/JO/jonoimage.jpg",
                                             "valueUnit": "string"
                                          },
                                          {
                                             "attributeType": "Feature",
                                             "attributeName": "AllowComparision",
                                             "isComparable": "false",
                                             "value": "false",
                                             "valueUnit": "bool"
                                          },
                                          {
                                             "attributeType": "Feature",
                                             "attributeName": "MoreDetail",
                                             "isComparable": "false",
                                             "value": [
                                                "Assists clients with their daily cashflow",
                                                "Provide bridging finance so clients can continue operating while waiting for incoming funds."
                                             ],
                                             "valueUnit": "array"
                                          },
                                          {
                                             "attributeType": "Feature",
                                             "attributeName": "DisplaySequence",
                                             "isComparable": "false",
                                             "value": 1,
                                             "valueUnit": "number"
                                          }
                                       ]
                                    },
                                    {
                                       "attributeGroupName": "clientEvidenceRequirement_Display",
                                       "productAttributes": [
                                          {
                                             "attributeType": "Display",
                                             "attributeName": "Identity Document",
                                             "isComparable": "false",
                                             "valueUnit": "bool"
                                          },
                                          {
                                             "attributeType": "Display",
                                             "attributeName": "Proof of Address",
                                             "isComparable": "false",
                                             "valueUnit": "bool"
                                          },
                                          {
                                             "attributeType": "Display",
                                             "attributeName": "Self-Certification Form",
                                             "isComparable": "false",
                                             "valueUnit": "bool"
                                          },
                                          {
                                             "attributeType": "Display",
                                             "attributeName": " First Resolution Details",
                                             "isComparable": "false",
                                             "valueUnit": "bool"
                                          },
                                          {
                                             "attributeType": "Display",
                                             "attributeName": " Annual Financial Statements",
                                             "isComparable": "false",
                                             "valueUnit": "bool"
                                          },
                                          {
                                             "attributeType": "Display",
                                             "attributeName": " Management Account",
                                             "isComparable": "false",
                                             "valueUnit": "bool"
                                          },
                                          {
                                             "attributeType": "Display",
                                             "attributeName": "Personal and Position Statements (PPS) ",
                                             "isComparable": "false",
                                             "valueUnit": "bool"
                                          }
                                       ]
                                    },
                                    {
                                       "attributeGroupName": "BusinessProcessExecutionConfiguration",
                                       "productAttributes": [
                                          {
                                             "attributeType": "int",
                                             "attributeName": "ApplicationCaptureExecutionTimeMinutes",
                                             "value": "30"
                                          },
                                          {
                                             "attributeType": "int",
                                             "attributeName": "ApplicationEndToEndExecutionTimeMinutes",
                                             "value": "90"
                                          },
                                          {
                                             "attributeType": "boolean",
                                             "attributeName": "requiresClientVerificationViaQA",
                                             "value": "true"
                                          },
                                          {
                                             "attributeType": "enum",
                                             "attributeName": "requiresClientVerificationAtPhase",
                                             "value": "GenerateOffer"
                                          },
                                          {
                                             "attributeType": "enum",
                                             "attributeName": "riskAnalysisMechanism",
                                             "value": "automated"
                                          },
                                          {
                                             "attributeType": "enum",
                                             "attributeName": "riskAnalysisMechanismIntent1",
                                             "value": "automated"
                                          },
                                          {
                                             "attributeType": "enum",
                                             "attributeName": "riskAnalysisMechanismIntent2",
                                             "value": "automated"
                                          },
                                          {
                                             "attributeType": "enum",
                                             "attributeName": "riskAnalysisMechanismIntent3",
                                             "value": "automated"
                                          },
                                          {
                                             "attributeType": "enum",
                                             "attributeName": "riskAnalysisMechanismIntent4",
                                             "value": "automated"
                                          },
                                          {
                                             "attributeType": "enum",
                                             "attributeName": "riskAnalysisMechanismIntent5",
                                             "value": "automated"
                                          },
                                          {
                                             "attributeType": "enum",
                                             "attributeName": "riskAnalysisMechanismIntent6",
                                             "value": "automated"
                                          },
                                          {
                                             "attributeType": "enum",
                                             "attributeName": "fullfillmentMechanism",
                                             "value": "automated"
                                          },
                                          {
                                             "attributeType": "enum",
                                             "attributeName": "productOnboardingProcessToExecute",
                                             "value": "enterpriseEndtoEnd"
                                          },
                                          {
                                             "attributeType": "boolean",
                                             "attributeName": "requiresSecurityAndCollatoralManagement",
                                             "value": "false"
                                          }
                                       ]
                                    }
                                 ]
                              }
                           ]
                        }
                     ]
                  }